cdk/ecs_codedeploy/__init__.py
cdk/ecs_codedeploy/py.typed
cdk/ecs_codedeploy/_jsii/__init__.py
cdk/ecs_codedeploy/_jsii/cdk-ecs-codedeploy@0.0.425.jsii.tgz
cdklabs_ecs_codedeploy-0.0.425.dist-info/LICENSE
cdklabs_ecs_codedeploy-0.0.425.dist-info/METADATA
cdklabs_ecs_codedeploy-0.0.425.dist-info/NOTICE
cdklabs_ecs_codedeploy-0.0.425.dist-info/WHEEL
cdklabs_ecs_codedeploy-0.0.425.dist-info/top_level.txt
cdklabs_ecs_codedeploy-0.0.425.dist-info/RECORD
